{
    "wallpaper": "/home/traveler/.config/wpg/wallpapers/hyprfog-2.png",
    "alpha": "100",

    "special": {
        "background": "#070f19",
        "foreground": "#92ffff",
        "cursor": "#92ffff"
    },
    "colors": {
        "color0": "#070f19",
        "color1": "#016769",
        "color2": "#01847d",
        "color3": "#019fa7",
        "color4": "#016c95",
        "color5": "#01a0d2",
        "color6": "#01aceb",
        "color7": "#6ce6e6",
        "color8": "#112641",
        "color9": "#018688",
        "color10": "#01aba2",
        "color11": "#01ced9",
        "color12": "#018cc2",
        "color13": "#01d0ff",
        "color14": "#01dfff",
        "color15": "#92ffff"
    }
}
