{
    "wallpaper": "/home/traveler/.config/wpg/wallpapers/commodore.jpg",
    "alpha": "100",

    "special": {
        "background": "#0b0509",
        "foreground": "#ffffff",
        "cursor": "#ffffff"
    },
    "colors": {
        "color0": "#0b0509",
        "color1": "#922262",
        "color2": "#aa4176",
        "color3": "#335eac",
        "color4": "#c753a2",
        "color5": "#15a1ea",
        "color6": "#63a8e3",
        "color7": "#dadada",
        "color8": "#2e1325",
        "color9": "#c92081",
        "color10": "#ec4599",
        "color11": "#3375ee",
        "color12": "#ff59d9",
        "color13": "#0ad6ff",
        "color14": "#6bdcff",
        "color15": "#ffffff"
    }
}
